featuretools_update_checker/__init__.py
featuretools_update_checker/functions.py
featuretools_update_checker/settings.py
featuretools_update_checker/utils.py
featuretools_update_checker/tests/__init__.py
featuretools_update_checker/tests/test_featuretools_update_checker.py
featuretools_update_checker-1.0.2.dist-info/LICENSE
featuretools_update_checker-1.0.2.dist-info/METADATA
featuretools_update_checker-1.0.2.dist-info/WHEEL
featuretools_update_checker-1.0.2.dist-info/entry_points.txt
featuretools_update_checker-1.0.2.dist-info/top_level.txt
featuretools_update_checker-1.0.2.dist-info/RECORD
