Metadata-Version: 2.1
Name: featuretools-update-checker
Version: 1.0.2
Summary: an update checker for featuretools
Home-page: http://featuretools.com
Author: Feature Labs, Inc.
Author-email: support@featurelabs.com
License: BSD 3-clause
Keywords: feature engineering data science machine learning
Platform: UNKNOWN
Classifier: Development Status :: 3 - Alpha
Classifier: Intended Audience :: Developers
Classifier: Programming Language :: Python :: 2.7
Classifier: Programming Language :: Python :: 3
Classifier: Programming Language :: Python :: 3.5
Classifier: Programming Language :: Python :: 3.6
Classifier: Programming Language :: Python :: 3.7
Requires-Python: >=2.7, <4
Requires-Dist: featuretools (>=0.8.0)
Requires-Dist: requests (>=2.22.0)
